pylint_pytest_plugin/__init__.py
pylint_pytest_plugin/_mock_add_message.py
pylint_pytest_plugin/_utils.py
pylint_pytest_plugin-0.1.0a2.dist-info/LICENSE
pylint_pytest_plugin-0.1.0a2.dist-info/METADATA
pylint_pytest_plugin-0.1.0a2.dist-info/WHEEL
pylint_pytest_plugin-0.1.0a2.dist-info/top_level.txt
pylint_pytest_plugin-0.1.0a2.dist-info/RECORD
